uvicontainer/__init__.py
uvicontainer/__main__.py
uvicontainer/_types.py
uvicontainer/config.py
uvicontainer/importer.py
uvicontainer/logging.py
uvicontainer/main.py
uvicontainer/server.py
uvicontainer/subprocess.py
uvicontainer/typing.py
uvicontainer/workers.py
uvicontainer/loops/__init__.py
uvicontainer/loops/asyncio.py
uvicontainer/loops/auto.py
uvicontainer/loops/uvloop.py
uvicontainer/protocols/__init__.py
uvicontainer/protocols/utils.py
uvicontainer/protocols/http/__init__.py
uvicontainer/protocols/http/auto.py
uvicontainer/protocols/http/flow_control.py
uvicontainer/protocols/http/h11_impl.py
uvicontainer/protocols/http/httptools_impl.py
uvicontainer/protocols/websockets/__init__.py
uvicontainer/protocols/websockets/auto.py
uvicontainer/protocols/websockets/websockets_impl.py
uvicontainer/protocols/websockets/wsproto_impl.py
uvicontainer/supervisors/__init__.py
uvicontainer/supervisors/basereload.py
uvicontainer/supervisors/multiprocess.py
uvicontainer/supervisors/statreload.py
uvicontainer/supervisors/watchgodreload.py
uvicontainer-0.1.1rc1.dist-info/LICENSE.md
uvicontainer-0.1.1rc1.dist-info/METADATA
uvicontainer-0.1.1rc1.dist-info/WHEEL
uvicontainer-0.1.1rc1.dist-info/entry_points.txt
uvicontainer-0.1.1rc1.dist-info/top_level.txt
uvicontainer-0.1.1rc1.dist-info/RECORD
